netspresso_inference_package/__init__.py
netspresso_inference_package/enums.py
netspresso_inference_package/exceptions.py
netspresso_inference_package/utils.py
netspresso_inference_package/inference/__init__.py
netspresso_inference_package/inference/abs.py
netspresso_inference_package/inference/data_loader.py
netspresso_inference_package/inference/inference_service.py
netspresso_inference_package/inference/onnx_inference.py
netspresso_inference_package/inference/tflite_inference.py
netspresso_inference_package-0.1.5.dist-info/METADATA
netspresso_inference_package-0.1.5.dist-info/WHEEL
netspresso_inference_package-0.1.5.dist-info/top_level.txt
netspresso_inference_package-0.1.5.dist-info/RECORD
