Metadata-Version: 2.1
Name: netspresso-inference-package
Version: 0.1.5
Summary: Inference module.
Home-page: https://github.com/nota-github/netspresso_inference_package
Author: NetsPresso
Author-email: netspresso@nota.ai
Classifier: Programming Language :: Python :: 3.8
Classifier: License :: OSI Approved :: MIT License
Classifier: Operating System :: OS Independent
Requires-Python: >=3.8
Requires-Dist: protobuf >=3.20.3
Requires-Dist: tensorflow >=2.8.0
Requires-Dist: onnx
Requires-Dist: onnxruntime
Requires-Dist: py7zr
Requires-Dist: rarfile
Requires-Dist: loguru
